[
  {
    "brand": {
      "id": 1,
      "name": "BRAND"
    },
    "code": "125264",
    "colorId": 45,
    "copy": "Remera cuello alto Livorno",
    "description": "Polera cuello alto, con detalle de puntilla ancha al tono en mangas.",
    "description2": "Realizada en viscosa elastizada",
    "description3": "Calce clásico",
    "id": 41050,
    "images": [
      "125264_45_1.jpg",
      "125264_7_1.jpg",
      "125264_8_1.jpg",
      "125264_8_2.jpg"
    ],
    "mainImage": "125264_45_1.jpg",
    "name": "LIVORNO POLERA",
    "price": 1300,
    "productLine": {
      "id": 3326,
      "name": "REMERAS",
      "parent": {
        "id": 3324,
        "name": "MUJER"
      }
    },
    "variation": {
      "id": "tipoVenta",
      "variationValues": [
        {
          "description": "VENTA NORMAL",
          "id": 2,
          "price": 1300,
          "variation": {
            "id": "color",
            "variationValues": [
              {
                "colorHex": "#5A5A3E",
                "description": "VERDE MILITAR",
                "id": 45,
                "price": 1300,
                "variation": {
                  "id": "size",
                  "variationValues": [
                    {
                      "description": "44",
                      "id": 54,
                      "price": 1300,
                      "productForSaleId": 5753985
                    }
                  ]
                }
              }
            ]
          }
        }
      ]
    },
    "variationName": "LIVORNO POLERA VERDE MILITAR",
    "productLineId": "3324"
  }
]