[
  {
    "brand": {
      "id": 1,
      "name": "BRAND"
    },
    "code": "125988",
    "colorId": 2,
    "description": "Buzo clásico con detalles en el frente de cinta a tono. Capucha forrada y cordones para ajustar.",
    "description2": "Realizado en rustico algodon",
    "description3": "Calce clásico",
    "id": 42158,
    "images": [
      "125988_2_1.jpg",
      "125988_2_2.jpg",
      "125988_74_1.jpg",
      "125988_74_2.jpg"
    ],
    "mainImage": "125988_2_1.jpg",
    "name": "ROSINA BUZO",
    "price": 1760,
    "productLine": {
      "id": 4756,
      "name": "BUZOS",
      "parent": {
        "id": 3324,
        "name": "MUJER"
      }
    },
    "variation": {
      "id": "tipoVenta",
      "variationValues": [
        {
          "description": "VENTA NORMAL",
          "id": 2,
          "price": 1760,
          "variation": {
            "id": "color",
            "variationValues": [
              {
                "colorHex": "#000000",
                "description": "NEGRO",
                "id": 2,
                "price": 1760,
                "variation": {
                  "id": "size",
                  "variationValues": [
                    {
                      "description": "44",
                      "id": 54,
                      "price": 1760,
                      "productForSaleId": 5753681
                    },
                    {
                      "description": "46",
                      "id": 55,
                      "price": 1760,
                      "productForSaleId": 5753679
                    },
                    {
                      "description": "48",
                      "id": 56,
                      "price": 1760,
                      "productForSaleId": 5753682
                    },
                    {
                      "description": "50",
                      "id": 101,
                      "price": 1760,
                      "productForSaleId": 5753678
                    }
                  ]
                }
              }
            ]
          }
        }
      ]
    },
    "variationName": "ROSINA BUZO NEGRO",
    "productLineId": "3324"
  }
]