[
  {
    "brand": {
      "id": 1,
      "name": "BRAND"
    },
    "code": "123914",
    "colorId": 2,
    "copy": "Vedetina Tricot Miranda",
    "description": "Bombacha vedetina con detalle de puntilla elastizada en delantero.",
    "description2": "Realizada en tricot y puntilla elastizada",
    "description3": "Calce al cuerpo",
    "id": 38938,
    "images": [
      "123914_1_1.jpg",
      "123914_1_2.jpg",
      "123914_1_3.jpg",
      "123914_1_4.jpg",
      "123914_1_5.jpg",
      "123914_1_6.jpg",
      "123914_1_7.jpg",
      "123914_2_1.jpg",
      "123914_2_2.jpg",
      "123914_2_3.jpg",
      "123914_2_4.jpg",
      "123914_3_1.jpg",
      "123914_3_2.jpg",
      "123914_3_3.jpg",
      "123914_3_4.jpg",
      "123914_452_1.jpg",
      "123914_452_2.jpg",
      "123914_452_3.jpg",
      "123914_452_4.jpg",
      "123914_452_5.jpg",
      "123914_452_6.jpg",
      "123914_452_7.jpg"
    ],
    "mainImage": "123914_2_1.jpg",
    "name": "MIRANDA VEDETINA",
    "price": 315,
    "price1": 450,
    "productLine": {
      "id": 3352,
      "name": "ROPA INTERIOR",
      "parent": {
        "id": 3324,
        "name": "MUJER"
      }
    },
    "variation": {
      "id": "tipoVenta",
      "variationValues": [
        {
          "description": "PRECIO REBAJADO",
          "id": 6,
          "price": 315,
          "price1": 450,
          "variation": {
            "id": "color",
            "variationValues": [
              {
                "colorHex": "#FFFFFF",
                "description": "BLANCO",
                "id": 1,
                "price": 315,
                "price1": 450,
                "variation": {
                  "id": "size",
                  "variationValues": [
                    {
                      "description": "2",
                      "id": 20,
                      "price": 315,
                      "price1": 450,
                      "productForSaleId": 5565770
                    },
                    {
                      "description": "3",
                      "id": 30,
                      "price": 315,
                      "price1": 450,
                      "productForSaleId": 5565769
                    },
                    {
                      "description": "4",
                      "id": 47,
                      "price": 315,
                      "price1": 450,
                      "productForSaleId": 5565771
                    }
                  ]
                }
              },
              {
                "colorHex": "#FFF8EC",
                "description": "NATURAL",
                "id": 3,
                "price": 315,
                "price1": 450,
                "variation": {
                  "id": "size",
                  "variationValues": [
                    {
                      "description": "2",
                      "id": 20,
                      "price": 315,
                      "price1": 450,
                      "productForSaleId": 5565777
                    },
                    {
                      "description": "3",
                      "id": 30,
                      "price": 315,
                      "price1": 450,
                      "productForSaleId": 5565776
                    },
                    {
                      "description": "4",
                      "id": 47,
                      "price": 315,
                      "price1": 450,
                      "productForSaleId": 5565775
                    }
                  ]
                }
              },
              {
                "colorHex": "#000000",
                "description": "NEGRO",
                "id": 2,
                "price": 315,
                "price1": 450,
                "variation": {
                  "id": "size",
                  "variationValues": [
                    {
                      "description": "2",
                      "id": 20,
                      "price": 315,
                      "price1": 450,
                      "productForSaleId": 5565774
                    },
                    {
                      "description": "3",
                      "id": 30,
                      "price": 315,
                      "price1": 450,
                      "productForSaleId": 5565773
                    },
                    {
                      "description": "4",
                      "id": 47,
                      "price": 315,
                      "price1": 450,
                      "productForSaleId": 5565772
                    }
                  ]
                }
              }
            ]
          }
        }
      ]
    },
    "variationName": "MIRANDA VEDETINA NEGRO"
  },
  {
    "brand": {
      "id": 1,
      "name": "BRAND"
    },
    "code": "123914",
    "colorId": 3,
    "copy": "Vedetina Tricot Miranda",
    "description": "Bombacha vedetina con detalle de puntilla elastizada en delantero.",
    "description2": "Realizada en tricot y puntilla elastizada",
    "description3": "Calce al cuerpo",
    "id": 38938,
    "images": [
      "123914_1_1.jpg",
      "123914_1_2.jpg",
      "123914_1_3.jpg",
      "123914_1_4.jpg",
      "123914_1_5.jpg",
      "123914_1_6.jpg",
      "123914_1_7.jpg",
      "123914_2_1.jpg",
      "123914_2_2.jpg",
      "123914_2_3.jpg",
      "123914_2_4.jpg",
      "123914_3_1.jpg",
      "123914_3_2.jpg",
      "123914_3_3.jpg",
      "123914_3_4.jpg",
      "123914_452_1.jpg",
      "123914_452_2.jpg",
      "123914_452_3.jpg",
      "123914_452_4.jpg",
      "123914_452_5.jpg",
      "123914_452_6.jpg",
      "123914_452_7.jpg"
    ],
    "mainImage": "123914_3_1.jpg",
    "name": "MIRANDA VEDETINA",
    "price": 315,
    "price1": 450,
    "productLine": {
      "id": 3352,
      "name": "ROPA INTERIOR",
      "parent": {
        "id": 3324,
        "name": "MUJER"
      }
    },
    "variation": {
      "id": "tipoVenta",
      "variationValues": [
        {
          "description": "PRECIO REBAJADO",
          "id": 6,
          "price": 315,
          "price1": 450,
          "variation": {
            "id": "color",
            "variationValues": [
              {
                "colorHex": "#FFFFFF",
                "description": "BLANCO",
                "id": 1,
                "price": 315,
                "price1": 450,
                "variation": {
                  "id": "size",
                  "variationValues": [
                    {
                      "description": "2",
                      "id": 20,
                      "price": 315,
                      "price1": 450,
                      "productForSaleId": 5565770
                    },
                    {
                      "description": "3",
                      "id": 30,
                      "price": 315,
                      "price1": 450,
                      "productForSaleId": 5565769
                    },
                    {
                      "description": "4",
                      "id": 47,
                      "price": 315,
                      "price1": 450,
                      "productForSaleId": 5565771
                    }
                  ]
                }
              },
              {
                "colorHex": "#FFF8EC",
                "description": "NATURAL",
                "id": 3,
                "price": 315,
                "price1": 450,
                "variation": {
                  "id": "size",
                  "variationValues": [
                    {
                      "description": "2",
                      "id": 20,
                      "price": 315,
                      "price1": 450,
                      "productForSaleId": 5565777
                    },
                    {
                      "description": "3",
                      "id": 30,
                      "price": 315,
                      "price1": 450,
                      "productForSaleId": 5565776
                    },
                    {
                      "description": "4",
                      "id": 47,
                      "price": 315,
                      "price1": 450,
                      "productForSaleId": 5565775
                    }
                  ]
                }
              },
              {
                "colorHex": "#000000",
                "description": "NEGRO",
                "id": 2,
                "price": 315,
                "price1": 450,
                "variation": {
                  "id": "size",
                  "variationValues": [
                    {
                      "description": "2",
                      "id": 20,
                      "price": 315,
                      "price1": 450,
                      "productForSaleId": 5565774
                    },
                    {
                      "description": "3",
                      "id": 30,
                      "price": 315,
                      "price1": 450,
                      "productForSaleId": 5565773
                    },
                    {
                      "description": "4",
                      "id": 47,
                      "price": 315,
                      "price1": 450,
                      "productForSaleId": 5565772
                    }
                  ]
                }
              }
            ]
          }
        }
      ]
    },
    "variationName": "MIRANDA VEDETINA NATURAL"
  },
  {
    "brand": {
      "id": 1,
      "name": "BRAND"
    },
    "code": "123914",
    "colorId": 1,
    "copy": "Vedetina Tricot Miranda",
    "description": "Bombacha vedetina con detalle de puntilla elastizada en delantero.",
    "description2": "Realizada en tricot y puntilla elastizada",
    "description3": "Calce al cuerpo",
    "id": 38938,
    "images": [
      "123914_1_1.jpg",
      "123914_1_2.jpg",
      "123914_1_3.jpg",
      "123914_1_4.jpg",
      "123914_1_5.jpg",
      "123914_1_6.jpg",
      "123914_1_7.jpg",
      "123914_2_1.jpg",
      "123914_2_2.jpg",
      "123914_2_3.jpg",
      "123914_2_4.jpg",
      "123914_3_1.jpg",
      "123914_3_2.jpg",
      "123914_3_3.jpg",
      "123914_3_4.jpg",
      "123914_452_1.jpg",
      "123914_452_2.jpg",
      "123914_452_3.jpg",
      "123914_452_4.jpg",
      "123914_452_5.jpg",
      "123914_452_6.jpg",
      "123914_452_7.jpg"
    ],
    "mainImage": "123914_1_1.jpg",
    "name": "MIRANDA VEDETINA",
    "price": 315,
    "price1": 450,
    "productLine": {
      "id": 3352,
      "name": "ROPA INTERIOR",
      "parent": {
        "id": 3324,
        "name": "MUJER"
      }
    },
    "variation": {
      "id": "tipoVenta",
      "variationValues": [
        {
          "description": "PRECIO REBAJADO",
          "id": 6,
          "price": 315,
          "price1": 450,
          "variation": {
            "id": "color",
            "variationValues": [
              {
                "colorHex": "#FFFFFF",
                "description": "BLANCO",
                "id": 1,
                "price": 315,
                "price1": 450,
                "variation": {
                  "id": "size",
                  "variationValues": [
                    {
                      "description": "2",
                      "id": 20,
                      "price": 315,
                      "price1": 450,
                      "productForSaleId": 5565770
                    },
                    {
                      "description": "3",
                      "id": 30,
                      "price": 315,
                      "price1": 450,
                      "productForSaleId": 5565769
                    },
                    {
                      "description": "4",
                      "id": 47,
                      "price": 315,
                      "price1": 450,
                      "productForSaleId": 5565771
                    }
                  ]
                }
              },
              {
                "colorHex": "#FFF8EC",
                "description": "NATURAL",
                "id": 3,
                "price": 315,
                "price1": 450,
                "variation": {
                  "id": "size",
                  "variationValues": [
                    {
                      "description": "2",
                      "id": 20,
                      "price": 315,
                      "price1": 450,
                      "productForSaleId": 5565777
                    },
                    {
                      "description": "3",
                      "id": 30,
                      "price": 315,
                      "price1": 450,
                      "productForSaleId": 5565776
                    },
                    {
                      "description": "4",
                      "id": 47,
                      "price": 315,
                      "price1": 450,
                      "productForSaleId": 5565775
                    }
                  ]
                }
              },
              {
                "colorHex": "#000000",
                "description": "NEGRO",
                "id": 2,
                "price": 315,
                "price1": 450,
                "variation": {
                  "id": "size",
                  "variationValues": [
                    {
                      "description": "2",
                      "id": 20,
                      "price": 315,
                      "price1": 450,
                      "productForSaleId": 5565774
                    },
                    {
                      "description": "3",
                      "id": 30,
                      "price": 315,
                      "price1": 450,
                      "productForSaleId": 5565773
                    },
                    {
                      "description": "4",
                      "id": 47,
                      "price": 315,
                      "price1": 450,
                      "productForSaleId": 5565772
                    }
                  ]
                }
              }
            ]
          }
        }
      ]
    },
    "variationName": "MIRANDA VEDETINA BLANCO"
  }
]