[
  {
    "brand": {
      "id": 1,
      "name": "BRAND"
    },
    "code": "124191",
    "colorId": 1398,
    "copy": "Necessaire Dina",
    "description": "Necessaire con cierre y forro interior. Ideal para viaje y organizar tus cosmeticos",
    "description2": "Realizado en pu 100%",
    "description3": "Calce clásico",
    "id": 39489,
    "images": [
      "124191_1398_1.jpg"
    ],
    "mainImage": "124191_1398_1.jpg",
    "name": "DINA NECESSAIRE",
    "price": 500,
    "productLine": {
      "id": 3350,
      "name": "ACCESORIOS",
      "parent": {
        "id": 3324,
        "name": "MUJER"
      }
    },
    "variation": {
      "id": "tipoVenta",
      "variationValues": [
        {
          "description": "VENTA NORMAL",
          "id": 2,
          "price": 500,
          "variation": {
            "id": "color",
            "variationValues": [
              {
                "colorHex": "#FFFFFF",
                "description": "ANIMAL PRINT",
                "id": 1398,
                "price": 500,
                "variation": {
                  "id": "size",
                  "variationValues": [
                    {
                      "description": "/",
                      "id": 1,
                      "price": 500,
                      "productForSaleId": 5550274
                    }
                  ]
                }
              }
            ]
          }
        }
      ]
    },
    "variationName": "DINA NECESSAIRE ANIMAL PRINT"
  }
]