[
  {
    "brand": {
      "id": 1,
      "name": "BRAND"
    },
    "code": "124216",
    "colorId": 2,
    "copy": "Colaless de microtul elastizado Olinda",
    "description": "Bombacha colaless con detalle de recortes en laterales hechos con microtul elastizado",
    "description2": "Realizado en tricot y microtul elastizado ",
    "description3": "Calce al cuerpo",
    "id": 39514,
    "images": [
      "124216_1252_1.jpg",
      "124216_1252_2.jpg",
      "124216_1252_3.jpg",
      "124216_1252_4.jpg"
    ],
    "mainImage": "124216_1252_1.jpg",
    "name": "OLINDA COLALESS",
    "price": 550,
    "price1": 790,
    "productLine": {
      "id": 3352,
      "name": "ROPA INTERIOR",
      "parent": {
        "id": 3324,
        "name": "MUJER"
      }
    },
    "variation": {
      "id": "tipoVenta",
      "variationValues": [
        {
          "description": "PRECIO REBAJADO",
          "id": 6,
          "price": 550,
          "price1": 790,
          "variation": {
            "id": "color",
            "variationValues": [
              {
                "colorHex": "#FFFFFF",
                "description": "BLANCO",
                "id": 1,
                "price": 550,
                "price1": 790,
                "variation": {
                  "id": "size",
                  "variationValues": [
                    {
                      "description": "100",
                      "id": 8,
                      "price": 550,
                      "price1": 790,
                      "productForSaleId": 5565808
                    },
                    {
                      "description": "105",
                      "id": 121,
                      "price": 550,
                      "price1": 790,
                      "productForSaleId": 5565807
                    },
                    {
                      "description": "90",
                      "id": 72,
                      "price": 550,
                      "price1": 790,
                      "productForSaleId": 5565809
                    },
                    {
                      "description": "95",
                      "id": 73,
                      "price": 550,
                      "price1": 790,
                      "productForSaleId": 5565806
                    }
                  ]
                }
              },
              {
                "colorHex": "#4D4D4D",
                "description": "GRIS - NEGRO",
                "id": 1252,
                "price": 550,
                "price1": 790,
                "variation": {
                  "id": "size",
                  "variationValues": [
                    {
                      "description": "1",
                      "id": 5,
                      "price": 550,
                      "price1": 790,
                      "productForSaleId": 5565805
                    },
                    {
                      "description": "2",
                      "id": 20,
                      "price": 550,
                      "price1": 790,
                      "productForSaleId": 5565803
                    },
                    {
                      "description": "3",
                      "id": 30,
                      "price": 550,
                      "price1": 790,
                      "productForSaleId": 5565804
                    },
                    {
                      "description": "4",
                      "id": 47,
                      "price": 550,
                      "price1": 790,
                      "productForSaleId": 5565802
                    }
                  ]
                }
              },
              {
                "colorHex": "#000000",
                "description": "NEGRO",
                "id": 2,
                "price": 550,
                "price1": 790,
                "variation": {
                  "id": "size",
                  "variationValues": [
                    {
                      "description": "100",
                      "id": 8,
                      "price": 550,
                      "price1": 790,
                      "productForSaleId": 5565810
                    },
                    {
                      "description": "105",
                      "id": 121,
                      "price": 550,
                      "price1": 790,
                      "productForSaleId": 5565811
                    },
                    {
                      "description": "90",
                      "id": 72,
                      "price": 550,
                      "price1": 790,
                      "productForSaleId": 5565813
                    },
                    {
                      "description": "95",
                      "id": 73,
                      "price": 550,
                      "price1": 790,
                      "productForSaleId": 5565812
                    }
                  ]
                }
              }
            ]
          }
        }
      ]
    },
    "variationName": "OLINDA COLALESS NEGRO"
  },
  {
    "brand": {
      "id": 1,
      "name": "BRAND"
    },
    "code": "124216",
    "colorId": 1252,
    "copy": "Colaless de microtul elastizado Olinda",
    "description": "Bombacha colaless con detalle de recortes en laterales hechos con microtul elastizado",
    "description2": "Realizado en tricot y microtul elastizado ",
    "description3": "Calce al cuerpo",
    "id": 39514,
    "images": [
      "124216_1252_1.jpg",
      "124216_1252_2.jpg",
      "124216_1252_3.jpg",
      "124216_1252_4.jpg"
    ],
    "mainImage": "124216_1252_1.jpg",
    "name": "OLINDA COLALESS",
    "price": 550,
    "price1": 790,
    "productLine": {
      "id": 3352,
      "name": "ROPA INTERIOR",
      "parent": {
        "id": 3324,
        "name": "MUJER"
      }
    },
    "variation": {
      "id": "tipoVenta",
      "variationValues": [
        {
          "description": "PRECIO REBAJADO",
          "id": 6,
          "price": 550,
          "price1": 790,
          "variation": {
            "id": "color",
            "variationValues": [
              {
                "colorHex": "#FFFFFF",
                "description": "BLANCO",
                "id": 1,
                "price": 550,
                "price1": 790,
                "variation": {
                  "id": "size",
                  "variationValues": [
                    {
                      "description": "100",
                      "id": 8,
                      "price": 550,
                      "price1": 790,
                      "productForSaleId": 5565808
                    },
                    {
                      "description": "105",
                      "id": 121,
                      "price": 550,
                      "price1": 790,
                      "productForSaleId": 5565807
                    },
                    {
                      "description": "90",
                      "id": 72,
                      "price": 550,
                      "price1": 790,
                      "productForSaleId": 5565809
                    },
                    {
                      "description": "95",
                      "id": 73,
                      "price": 550,
                      "price1": 790,
                      "productForSaleId": 5565806
                    }
                  ]
                }
              },
              {
                "colorHex": "#4D4D4D",
                "description": "GRIS - NEGRO",
                "id": 1252,
                "price": 550,
                "price1": 790,
                "variation": {
                  "id": "size",
                  "variationValues": [
                    {
                      "description": "1",
                      "id": 5,
                      "price": 550,
                      "price1": 790,
                      "productForSaleId": 5565805
                    },
                    {
                      "description": "2",
                      "id": 20,
                      "price": 550,
                      "price1": 790,
                      "productForSaleId": 5565803
                    },
                    {
                      "description": "3",
                      "id": 30,
                      "price": 550,
                      "price1": 790,
                      "productForSaleId": 5565804
                    },
                    {
                      "description": "4",
                      "id": 47,
                      "price": 550,
                      "price1": 790,
                      "productForSaleId": 5565802
                    }
                  ]
                }
              },
              {
                "colorHex": "#000000",
                "description": "NEGRO",
                "id": 2,
                "price": 550,
                "price1": 790,
                "variation": {
                  "id": "size",
                  "variationValues": [
                    {
                      "description": "100",
                      "id": 8,
                      "price": 550,
                      "price1": 790,
                      "productForSaleId": 5565810
                    },
                    {
                      "description": "105",
                      "id": 121,
                      "price": 550,
                      "price1": 790,
                      "productForSaleId": 5565811
                    },
                    {
                      "description": "90",
                      "id": 72,
                      "price": 550,
                      "price1": 790,
                      "productForSaleId": 5565813
                    },
                    {
                      "description": "95",
                      "id": 73,
                      "price": 550,
                      "price1": 790,
                      "productForSaleId": 5565812
                    }
                  ]
                }
              }
            ]
          }
        }
      ]
    },
    "variationName": "OLINDA COLALESS GRIS - NEGRO"
  },
  {
    "brand": {
      "id": 1,
      "name": "BRAND"
    },
    "code": "124216",
    "colorId": 1,
    "copy": "Colaless de microtul elastizado Olinda",
    "description": "Bombacha colaless con detalle de recortes en laterales hechos con microtul elastizado",
    "description2": "Realizado en tricot y microtul elastizado ",
    "description3": "Calce al cuerpo",
    "id": 39514,
    "images": [
      "124216_1252_1.jpg",
      "124216_1252_2.jpg",
      "124216_1252_3.jpg",
      "124216_1252_4.jpg"
    ],
    "mainImage": "124216_1252_1.jpg",
    "name": "OLINDA COLALESS",
    "price": 550,
    "price1": 790,
    "productLine": {
      "id": 3352,
      "name": "ROPA INTERIOR",
      "parent": {
        "id": 3324,
        "name": "MUJER"
      }
    },
    "variation": {
      "id": "tipoVenta",
      "variationValues": [
        {
          "description": "PRECIO REBAJADO",
          "id": 6,
          "price": 550,
          "price1": 790,
          "variation": {
            "id": "color",
            "variationValues": [
              {
                "colorHex": "#FFFFFF",
                "description": "BLANCO",
                "id": 1,
                "price": 550,
                "price1": 790,
                "variation": {
                  "id": "size",
                  "variationValues": [
                    {
                      "description": "100",
                      "id": 8,
                      "price": 550,
                      "price1": 790,
                      "productForSaleId": 5565808
                    },
                    {
                      "description": "105",
                      "id": 121,
                      "price": 550,
                      "price1": 790,
                      "productForSaleId": 5565807
                    },
                    {
                      "description": "90",
                      "id": 72,
                      "price": 550,
                      "price1": 790,
                      "productForSaleId": 5565809
                    },
                    {
                      "description": "95",
                      "id": 73,
                      "price": 550,
                      "price1": 790,
                      "productForSaleId": 5565806
                    }
                  ]
                }
              },
              {
                "colorHex": "#4D4D4D",
                "description": "GRIS - NEGRO",
                "id": 1252,
                "price": 550,
                "price1": 790,
                "variation": {
                  "id": "size",
                  "variationValues": [
                    {
                      "description": "1",
                      "id": 5,
                      "price": 550,
                      "price1": 790,
                      "productForSaleId": 5565805
                    },
                    {
                      "description": "2",
                      "id": 20,
                      "price": 550,
                      "price1": 790,
                      "productForSaleId": 5565803
                    },
                    {
                      "description": "3",
                      "id": 30,
                      "price": 550,
                      "price1": 790,
                      "productForSaleId": 5565804
                    },
                    {
                      "description": "4",
                      "id": 47,
                      "price": 550,
                      "price1": 790,
                      "productForSaleId": 5565802
                    }
                  ]
                }
              },
              {
                "colorHex": "#000000",
                "description": "NEGRO",
                "id": 2,
                "price": 550,
                "price1": 790,
                "variation": {
                  "id": "size",
                  "variationValues": [
                    {
                      "description": "100",
                      "id": 8,
                      "price": 550,
                      "price1": 790,
                      "productForSaleId": 5565810
                    },
                    {
                      "description": "105",
                      "id": 121,
                      "price": 550,
                      "price1": 790,
                      "productForSaleId": 5565811
                    },
                    {
                      "description": "90",
                      "id": 72,
                      "price": 550,
                      "price1": 790,
                      "productForSaleId": 5565813
                    },
                    {
                      "description": "95",
                      "id": 73,
                      "price": 550,
                      "price1": 790,
                      "productForSaleId": 5565812
                    }
                  ]
                }
              }
            ]
          }
        }
      ]
    },
    "variationName": "OLINDA COLALESS BLANCO"
  }
]