[
  {
    "brand": {
      "id": 1,
      "name": "BRAND"
    },
    "code": "124333",
    "colorId": 24,
    "description": "Remera escote redondo manga corta, con impactante estampa en delantero.",
    "description2": "Realizada en jersey flame",
    "description3": "Calce clásico",
    "id": 39674,
    "images": [
      "124333_24_1.jpg",
      "124333_24_9.jpg"
    ],
    "mainImage": "124333_24_1.jpg",
    "name": "MARCEL REMERA",
    "price": 800,
    "productLine": {
      "id": 3355,
      "name": "REMERAS",
      "parent": {
        "id": 3325,
        "name": "HOMBRE"
      }
    },
    "variation": {
      "id": "tipoVenta",
      "variationValues": [
        {
          "description": "VENTA NORMAL",
          "id": 2,
          "price": 800,
          "variation": {
            "id": "color",
            "variationValues": [
              {
                "colorHex": "#D7C339",
                "description": "MOSTAZA",
                "id": 24,
                "price": 800,
                "variation": {
                  "id": "size",
                  "variationValues": [
                    {
                      "description": "1",
                      "id": 5,
                      "price": 800,
                      "productForSaleId": 5548396
                    },
                    {
                      "description": "2",
                      "id": 20,
                      "price": 800,
                      "productForSaleId": 5548397
                    },
                    {
                      "description": "3",
                      "id": 30,
                      "price": 800,
                      "productForSaleId": 5548394
                    },
                    {
                      "description": "4",
                      "id": 47,
                      "price": 800,
                      "productForSaleId": 5548395
                    },
                    {
                      "description": "5",
                      "id": 57,
                      "price": 800,
                      "productForSaleId": 5548398
                    }
                  ]
                }
              }
            ]
          }
        }
      ]
    },
    "variationName": "MARCEL REMERA MOSTAZA"
  }
]