[
  {
    "brand": {
      "id": 1,
      "name": "BRAND"
    },
    "code": "125078",
    "colorId": 2,
    "copy": "Remera cuello redondo Edesia",
    "description": "Remera escote en V con detalle de ruedo irregular, más largo en espalda que en delantero y tajos laterales. Impactante estampa en delantero.",
    "description2": "Realizada en jersey algodon",
    "description3": "Calce clásico",
    "id": 40837,
    "images": [
      "125078_2_1.jpg"
    ],
    "mainImage": "125078_2_1.jpg",
    "name": "EDESIA REMERA",
    "price": 945,
    "price1": 1350,
    "productLine": {
      "id": 3326,
      "name": "REMERAS",
      "parent": {
        "id": 3324,
        "name": "MUJER"
      }
    },
    "variation": {
      "id": "tipoVenta",
      "variationValues": [
        {
          "description": "PRECIO REBAJADO",
          "id": 6,
          "price": 945,
          "price1": 1350,
          "variation": {
            "id": "color",
            "variationValues": [
              {
                "colorHex": "#000000",
                "description": "NEGRO",
                "id": 2,
                "price": 945,
                "price1": 1350,
                "variation": {
                  "id": "size",
                  "variationValues": [
                    {
                      "description": "40",
                      "id": 50,
                      "price": 945,
                      "price1": 1350,
                      "productForSaleId": 5551348
                    },
                    {
                      "description": "42",
                      "id": 52,
                      "price": 945,
                      "price1": 1350,
                      "productForSaleId": 5551346
                    },
                    {
                      "description": "44",
                      "id": 54,
                      "price": 945,
                      "price1": 1350,
                      "productForSaleId": 5551350
                    },
                    {
                      "description": "46",
                      "id": 55,
                      "price": 945,
                      "price1": 1350,
                      "productForSaleId": 5551347
                    },
                    {
                      "description": "48",
                      "id": 56,
                      "price": 945,
                      "price1": 1350,
                      "productForSaleId": 5551349
                    },
                    {
                      "description": "50",
                      "id": 101,
                      "price": 945,
                      "price1": 1350,
                      "productForSaleId": 5551351
                    }
                  ]
                }
              }
            ]
          }
        }
      ]
    },
    "variationName": "EDESIA REMERA NEGRO"
  }
]